quickspikes/intracellular.py
quickspikes/tools.py
quickspikes/__init__.py
quickspikes/spikes.pyx
quickspikes/spikes.cpython-314-darwin.so
quickspikes-2.0.7.dist-info/RECORD
quickspikes-2.0.7.dist-info/WHEEL
quickspikes-2.0.7.dist-info/top_level.txt
quickspikes-2.0.7.dist-info/METADATA
quickspikes-2.0.7.dist-info/licenses/COPYING
