Metadata-Version: 2.4
Name: quickspikes
Version: 2.0.7
Summary: Advanced Recording Format Tools
Author-email: C Daniel Meliza <dan@meliza.org>
Maintainer-email: C Daniel Meliza <dan@meliza.org>
License: BSD-3-Clause
Project-URL: homepage, https://github.com/melizalab/quickspikes
Classifier: Development Status :: 5 - Production/Stable
Classifier: Intended Audience :: Science/Research
Classifier: Programming Language :: Python
Classifier: Programming Language :: Python :: 3.7
Classifier: Programming Language :: Python :: 3.8
Classifier: Programming Language :: Python :: 3.9
Classifier: Programming Language :: Python :: 3.10
Classifier: Programming Language :: Python :: 3.11
Classifier: Programming Language :: Python :: 3.12
Classifier: Programming Language :: Python :: Implementation :: CPython
Classifier: Programming Language :: Python :: Implementation :: PyPy
Classifier: Topic :: Scientific/Engineering
Classifier: Operating System :: Unix
Classifier: Operating System :: POSIX :: Linux
Classifier: Operating System :: MacOS :: MacOS X
Classifier: Operating System :: Microsoft :: Windows
Classifier: Natural Language :: English
Requires-Python: >=3.9
License-File: COPYING
Requires-Dist: numpy>=2.0.2
Dynamic: license-file
